{
  "date": "2025-12-31",
  "unit": "EUR/MWh",
  "zones": {
    "LV": [
      { "hour": 0, "price": 77.22 },
      { "hour": 1, "price": 69.03 },
      { "hour": 2, "price": 59.74 },
      { "hour": 3, "price": 57.01 },
      { "hour": 4, "price": 56.2 },
      { "hour": 5, "price": 56.21 },
      { "hour": 6, "price": 67.33 },
      { "hour": 7, "price": 71.13 },
      { "hour": 8, "price": 78.6 },
      { "hour": 9, "price": 92.73 },
      { "hour": 10, "price": 90.29 },
      { "hour": 11, "price": 89.4 },
      { "hour": 12, "price": 82.92 },
      { "hour": 13, "price": 83.05 },
      { "hour": 14, "price": 112.03 },
      { "hour": 15, "price": 132.83 },
      { "hour": 16, "price": 137.67 },
      { "hour": 17, "price": 161.88 },
      { "hour": 18, "price": 148.85 },
      { "hour": 19, "price": 152.11 },
      { "hour": 20, "price": 140.12 },
      { "hour": 21, "price": 131.53 },
      { "hour": 22, "price": 130.04 },
      { "hour": 23, "price": 115.84 }
    ],
    "EE": [
      { "hour": 0, "price": 77.22 },
      { "hour": 1, "price": 65.39 },
      { "hour": 2, "price": 54.96 },
      { "hour": 3, "price": 52.54 },
      { "hour": 4, "price": 52.23 },
      { "hour": 5, "price": 52.51 },
      { "hour": 6, "price": 66.75 },
      { "hour": 7, "price": 71.13 },
      { "hour": 8, "price": 78.6 },
      { "hour": 9, "price": 92.73 },
      { "hour": 10, "price": 90.29 },
      { "hour": 11, "price": 89.4 },
      { "hour": 12, "price": 82.92 },
      { "hour": 13, "price": 83.05 },
      { "hour": 14, "price": 112.03 },
      { "hour": 15, "price": 132.83 },
      { "hour": 16, "price": 137.67 },
      { "hour": 17, "price": 161.88 },
      { "hour": 18, "price": 148.85 },
      { "hour": 19, "price": 152.11 },
      { "hour": 20, "price": 140.12 },
      { "hour": 21, "price": 131.53 },
      { "hour": 22, "price": 130.04 },
      { "hour": 23, "price": 115.84 }
    ],
    "LT": [
      { "hour": 0, "price": 77.22 },
      { "hour": 1, "price": 69.03 },
      { "hour": 2, "price": 59.74 },
      { "hour": 3, "price": 57.01 },
      { "hour": 4, "price": 56.2 },
      { "hour": 5, "price": 56.21 },
      { "hour": 6, "price": 67.33 },
      { "hour": 7, "price": 71.13 },
      { "hour": 8, "price": 78.6 },
      { "hour": 9, "price": 92.73 },
      { "hour": 10, "price": 90.29 },
      { "hour": 11, "price": 89.4 },
      { "hour": 12, "price": 82.92 },
      { "hour": 13, "price": 83.05 },
      { "hour": 14, "price": 112.03 },
      { "hour": 15, "price": 132.83 },
      { "hour": 16, "price": 137.67 },
      { "hour": 17, "price": 161.88 },
      { "hour": 18, "price": 148.85 },
      { "hour": 19, "price": 152.11 },
      { "hour": 20, "price": 140.12 },
      { "hour": 21, "price": 131.53 },
      { "hour": 22, "price": 130.04 },
      { "hour": 23, "price": 115.84 }
    ]
  }
}
