{
  "date": "2025-07-16",
  "unit": "EUR/MWh",
  "zones": {
    "LV": [
      { "hour": 0, "price": 62.34 },
      { "hour": 1, "price": 62.22 },
      { "hour": 2, "price": 57.93 },
      { "hour": 3, "price": 54.74 },
      { "hour": 4, "price": 46.12 },
      { "hour": 5, "price": 19.94 },
      { "hour": 6, "price": 89.11 },
      { "hour": 7, "price": 99.91 },
      { "hour": 8, "price": 98.09 },
      { "hour": 9, "price": 111.73 },
      { "hour": 10, "price": 70.55 },
      { "hour": 11, "price": 61.68 },
      { "hour": 12, "price": 64.07 },
      { "hour": 13, "price": 60.63 },
      { "hour": 14, "price": 56.87 },
      { "hour": 15, "price": 51.25 },
      { "hour": 16, "price": 53.99 },
      { "hour": 17, "price": 56.76 },
      { "hour": 18, "price": 63.91 },
      { "hour": 19, "price": 68.48 },
      { "hour": 20, "price": 164.5 },
      { "hour": 21, "price": 192.54 },
      { "hour": 22, "price": 150.5 },
      { "hour": 23, "price": 125.21 }
    ],
    "EE": [
      { "hour": 0, "price": 12.91 },
      { "hour": 1, "price": 62.22 },
      { "hour": 2, "price": 40.01 },
      { "hour": 3, "price": 12.92 },
      { "hour": 4, "price": 7.06 },
      { "hour": 5, "price": 6.56 },
      { "hour": 6, "price": 25.09 },
      { "hour": 7, "price": 40.01 },
      { "hour": 8, "price": 25.03 },
      { "hour": 9, "price": 32.94 },
      { "hour": 10, "price": 18.47 },
      { "hour": 11, "price": 9.02 },
      { "hour": 12, "price": 8.94 },
      { "hour": 13, "price": 11.51 },
      { "hour": 14, "price": 10.79 },
      { "hour": 15, "price": 9.91 },
      { "hour": 16, "price": 10.83 },
      { "hour": 17, "price": 10.12 },
      { "hour": 18, "price": 12.16 },
      { "hour": 19, "price": 68.48 },
      { "hour": 20, "price": 164.5 },
      { "hour": 21, "price": 192.54 },
      { "hour": 22, "price": 150.5 },
      { "hour": 23, "price": 125.21 }
    ],
    "LT": [
      { "hour": 0, "price": 62.34 },
      { "hour": 1, "price": 62.22 },
      { "hour": 2, "price": 57.93 },
      { "hour": 3, "price": 54.74 },
      { "hour": 4, "price": 46.12 },
      { "hour": 5, "price": 19.94 },
      { "hour": 6, "price": 89.11 },
      { "hour": 7, "price": 99.91 },
      { "hour": 8, "price": 98.09 },
      { "hour": 9, "price": 111.73 },
      { "hour": 10, "price": 70.55 },
      { "hour": 11, "price": 61.68 },
      { "hour": 12, "price": 64.07 },
      { "hour": 13, "price": 60.63 },
      { "hour": 14, "price": 56.87 },
      { "hour": 15, "price": 51.25 },
      { "hour": 16, "price": 53.99 },
      { "hour": 17, "price": 56.76 },
      { "hour": 18, "price": 63.91 },
      { "hour": 19, "price": 68.48 },
      { "hour": 20, "price": 164.5 },
      { "hour": 21, "price": 192.54 },
      { "hour": 22, "price": 150.5 },
      { "hour": 23, "price": 125.21 }
    ]
  }
}
