{
  "date": "2025-08-16",
  "unit": "EUR/MWh",
  "zones": {
    "LV": [
      { "hour": 0, "price": 95.94 },
      { "hour": 1, "price": 35.99 },
      { "hour": 2, "price": 32.21 },
      { "hour": 3, "price": 37.67 },
      { "hour": 4, "price": 36.86 },
      { "hour": 5, "price": 66.99 },
      { "hour": 6, "price": 68.71 },
      { "hour": 7, "price": 72.05 },
      { "hour": 8, "price": 67.99 },
      { "hour": 9, "price": 64.51 },
      { "hour": 10, "price": 60.04 },
      { "hour": 11, "price": 16.44 },
      { "hour": 12, "price": 3.8 },
      { "hour": 13, "price": 0.44 },
      { "hour": 14, "price": 0.01 },
      { "hour": 15, "price": 0.04 },
      { "hour": 16, "price": 0.04 },
      { "hour": 17, "price": 3.5 },
      { "hour": 18, "price": 8 },
      { "hour": 19, "price": 68.44 },
      { "hour": 20, "price": 70.9 },
      { "hour": 21, "price": 77.36 },
      { "hour": 22, "price": 81.4 },
      { "hour": 23, "price": 78.72 }
    ],
    "EE": [
      { "hour": 0, "price": 20.84 },
      { "hour": 1, "price": 20.78 },
      { "hour": 2, "price": 20.77 },
      { "hour": 3, "price": 20.77 },
      { "hour": 4, "price": 20.76 },
      { "hour": 5, "price": 20.76 },
      { "hour": 6, "price": 20.76 },
      { "hour": 7, "price": 20.76 },
      { "hour": 8, "price": 4.6 },
      { "hour": 9, "price": 2.77 },
      { "hour": 10, "price": 2.78 },
      { "hour": 11, "price": 3.51 },
      { "hour": 12, "price": 2.92 },
      { "hour": 13, "price": 0.44 },
      { "hour": 14, "price": 0.01 },
      { "hour": 15, "price": 0.04 },
      { "hour": 16, "price": 0.04 },
      { "hour": 17, "price": 3.5 },
      { "hour": 18, "price": 8 },
      { "hour": 19, "price": 20.83 },
      { "hour": 20, "price": 20.84 },
      { "hour": 21, "price": 20.84 },
      { "hour": 22, "price": 20.84 },
      { "hour": 23, "price": 21.02 }
    ],
    "LT": [
      { "hour": 0, "price": 95.94 },
      { "hour": 1, "price": 35.99 },
      { "hour": 2, "price": 32.21 },
      { "hour": 3, "price": 37.67 },
      { "hour": 4, "price": 36.86 },
      { "hour": 5, "price": 66.99 },
      { "hour": 6, "price": 68.71 },
      { "hour": 7, "price": 72.05 },
      { "hour": 8, "price": 67.99 },
      { "hour": 9, "price": 64.51 },
      { "hour": 10, "price": 60.04 },
      { "hour": 11, "price": 16.44 },
      { "hour": 12, "price": 3.8 },
      { "hour": 13, "price": 0.44 },
      { "hour": 14, "price": 0.01 },
      { "hour": 15, "price": 0.04 },
      { "hour": 16, "price": 0.04 },
      { "hour": 17, "price": 3.5 },
      { "hour": 18, "price": 8 },
      { "hour": 19, "price": 68.44 },
      { "hour": 20, "price": 70.9 },
      { "hour": 21, "price": 77.36 },
      { "hour": 22, "price": 81.4 },
      { "hour": 23, "price": 78.72 }
    ]
  }
}
