{
  "date": "2025-12-28",
  "unit": "EUR/MWh",
  "zones": {
    "LV": [
      { "hour": 0, "price": 0.02 },
      { "hour": 1, "price": -0.01 },
      { "hour": 2, "price": 0 },
      { "hour": 3, "price": 0 },
      { "hour": 4, "price": 0.01 },
      { "hour": 5, "price": 0.45 },
      { "hour": 6, "price": 1.85 },
      { "hour": 7, "price": 2.04 },
      { "hour": 8, "price": 3.02 },
      { "hour": 9, "price": 4.1 },
      { "hour": 10, "price": 5.41 },
      { "hour": 11, "price": 5.65 },
      { "hour": 12, "price": 5.36 },
      { "hour": 13, "price": 4.11 },
      { "hour": 14, "price": 4.01 },
      { "hour": 15, "price": 13.54 },
      { "hour": 16, "price": 40.72 },
      { "hour": 17, "price": 61.9 },
      { "hour": 18, "price": 60.77 },
      { "hour": 19, "price": 61.38 },
      { "hour": 20, "price": 46.72 },
      { "hour": 21, "price": 40.79 },
      { "hour": 22, "price": 40.27 },
      { "hour": 23, "price": 17.51 }
    ],
    "EE": [
      { "hour": 0, "price": 0.02 },
      { "hour": 1, "price": -0.01 },
      { "hour": 2, "price": 0 },
      { "hour": 3, "price": 0 },
      { "hour": 4, "price": 0.01 },
      { "hour": 5, "price": 0.45 },
      { "hour": 6, "price": 1.85 },
      { "hour": 7, "price": 2.04 },
      { "hour": 8, "price": 3.02 },
      { "hour": 9, "price": 4.1 },
      { "hour": 10, "price": 4.88 },
      { "hour": 11, "price": 5.65 },
      { "hour": 12, "price": 3.72 },
      { "hour": 13, "price": 4.11 },
      { "hour": 14, "price": 4.01 },
      { "hour": 15, "price": 13.54 },
      { "hour": 16, "price": 40.72 },
      { "hour": 17, "price": 61.9 },
      { "hour": 18, "price": 60.77 },
      { "hour": 19, "price": 61.38 },
      { "hour": 20, "price": 46.72 },
      { "hour": 21, "price": 40.79 },
      { "hour": 22, "price": 40.27 },
      { "hour": 23, "price": 17.51 }
    ],
    "LT": [
      { "hour": 0, "price": 0.02 },
      { "hour": 1, "price": -0.01 },
      { "hour": 2, "price": 0 },
      { "hour": 3, "price": 0 },
      { "hour": 4, "price": 0.01 },
      { "hour": 5, "price": 0.45 },
      { "hour": 6, "price": 1.85 },
      { "hour": 7, "price": 2.04 },
      { "hour": 8, "price": 3.02 },
      { "hour": 9, "price": 4.1 },
      { "hour": 10, "price": 5.41 },
      { "hour": 11, "price": 5.65 },
      { "hour": 12, "price": 5.36 },
      { "hour": 13, "price": 4.11 },
      { "hour": 14, "price": 4.01 },
      { "hour": 15, "price": 13.54 },
      { "hour": 16, "price": 40.72 },
      { "hour": 17, "price": 61.9 },
      { "hour": 18, "price": 60.77 },
      { "hour": 19, "price": 61.38 },
      { "hour": 20, "price": 46.72 },
      { "hour": 21, "price": 40.79 },
      { "hour": 22, "price": 40.27 },
      { "hour": 23, "price": 17.51 }
    ]
  }
}
