{
  "date": "2025-10-01",
  "unit": "EUR/MWh",
  "zones": {
    "LV": [
      { "hour": 0, "price": 74.42 },
      { "hour": 1, "price": 87.78 },
      { "hour": 2, "price": 83.87 },
      { "hour": 3, "price": 81.25 },
      { "hour": 4, "price": 90.03 },
      { "hour": 5, "price": 88.91 },
      { "hour": 6, "price": 95.59 },
      { "hour": 7, "price": 124.81 },
      { "hour": 8, "price": 181.91 },
      { "hour": 9, "price": 144.33 },
      { "hour": 10, "price": 110.36 },
      { "hour": 11, "price": 88.59 },
      { "hour": 12, "price": 87.14 },
      { "hour": 13, "price": 101.64 },
      { "hour": 14, "price": 100.24 },
      { "hour": 15, "price": 88.15 },
      { "hour": 16, "price": 111.92 },
      { "hour": 17, "price": 137.11 },
      { "hour": 18, "price": 149.26 },
      { "hour": 19, "price": 256.09 },
      { "hour": 20, "price": 341.23 },
      { "hour": 21, "price": 153.69 },
      { "hour": 22, "price": 114.19 },
      { "hour": 23, "price": 98.04 }
    ],
    "EE": [
      { "hour": 0, "price": 41.57 },
      { "hour": 1, "price": 87.78 },
      { "hour": 2, "price": 83.87 },
      { "hour": 3, "price": 72.59 },
      { "hour": 4, "price": 90.03 },
      { "hour": 5, "price": 80.4 },
      { "hour": 6, "price": 95.59 },
      { "hour": 7, "price": 124.81 },
      { "hour": 8, "price": 181.91 },
      { "hour": 9, "price": 144.33 },
      { "hour": 10, "price": 103.53 },
      { "hour": 11, "price": 88.59 },
      { "hour": 12, "price": 87.14 },
      { "hour": 13, "price": 101.64 },
      { "hour": 14, "price": 100.24 },
      { "hour": 15, "price": 88.15 },
      { "hour": 16, "price": 111.92 },
      { "hour": 17, "price": 137.11 },
      { "hour": 18, "price": 149.26 },
      { "hour": 19, "price": 256.09 },
      { "hour": 20, "price": 341.23 },
      { "hour": 21, "price": 153.69 },
      { "hour": 22, "price": 114.19 },
      { "hour": 23, "price": 98.04 }
    ],
    "LT": [
      { "hour": 0, "price": 74.42 },
      { "hour": 1, "price": 87.78 },
      { "hour": 2, "price": 83.87 },
      { "hour": 3, "price": 81.25 },
      { "hour": 4, "price": 90.03 },
      { "hour": 5, "price": 88.91 },
      { "hour": 6, "price": 95.59 },
      { "hour": 7, "price": 124.81 },
      { "hour": 8, "price": 181.91 },
      { "hour": 9, "price": 144.33 },
      { "hour": 10, "price": 110.36 },
      { "hour": 11, "price": 88.59 },
      { "hour": 12, "price": 87.14 },
      { "hour": 13, "price": 101.64 },
      { "hour": 14, "price": 100.24 },
      { "hour": 15, "price": 88.15 },
      { "hour": 16, "price": 111.92 },
      { "hour": 17, "price": 137.11 },
      { "hour": 18, "price": 149.26 },
      { "hour": 19, "price": 256.09 },
      { "hour": 20, "price": 341.23 },
      { "hour": 21, "price": 153.69 },
      { "hour": 22, "price": 114.19 },
      { "hour": 23, "price": 98.04 }
    ]
  }
}
