{
  "date": "2026-03-05",
  "unit": "EUR/MWh",
  "zones": {
    "LV": [
      { "hour": 0, "price": 47.39 },
      { "hour": 1, "price": 114.15 },
      { "hour": 2, "price": 107.36 },
      { "hour": 3, "price": 106.67 },
      { "hour": 4, "price": 106.08 },
      { "hour": 5, "price": 107.03 },
      { "hour": 6, "price": 122.18 },
      { "hour": 7, "price": 148.44 },
      { "hour": 8, "price": 170.18 },
      { "hour": 9, "price": 132.58 },
      { "hour": 10, "price": 96.54 },
      { "hour": 11, "price": 68.24 },
      { "hour": 12, "price": 59.02 },
      { "hour": 13, "price": 57.9 },
      { "hour": 14, "price": 58.21 },
      { "hour": 15, "price": 61.25 },
      { "hour": 16, "price": 88.27 },
      { "hour": 17, "price": 124.57 },
      { "hour": 18, "price": 175.44 },
      { "hour": 19, "price": 189.94 },
      { "hour": 20, "price": 153.86 },
      { "hour": 21, "price": 147.88 },
      { "hour": 22, "price": 131.82 },
      { "hour": 23, "price": 132 }
    ],
    "EE": [
      { "hour": 0, "price": 45.39 },
      { "hour": 1, "price": 100.89 },
      { "hour": 2, "price": 100.9 },
      { "hour": 3, "price": 106.67 },
      { "hour": 4, "price": 100.89 },
      { "hour": 5, "price": 105.48 },
      { "hour": 6, "price": 76.68 },
      { "hour": 7, "price": 130.79 },
      { "hour": 8, "price": 170.18 },
      { "hour": 9, "price": 130.77 },
      { "hour": 10, "price": 96.54 },
      { "hour": 11, "price": 68.24 },
      { "hour": 12, "price": 59.02 },
      { "hour": 13, "price": 57.9 },
      { "hour": 14, "price": 58.21 },
      { "hour": 15, "price": 61.25 },
      { "hour": 16, "price": 88.27 },
      { "hour": 17, "price": 124.57 },
      { "hour": 18, "price": 175.44 },
      { "hour": 19, "price": 189.94 },
      { "hour": 20, "price": 153.86 },
      { "hour": 21, "price": 147.88 },
      { "hour": 22, "price": 131.82 },
      { "hour": 23, "price": 132 }
    ],
    "LT": [
      { "hour": 0, "price": 47.39 },
      { "hour": 1, "price": 114.15 },
      { "hour": 2, "price": 107.36 },
      { "hour": 3, "price": 106.67 },
      { "hour": 4, "price": 106.08 },
      { "hour": 5, "price": 107.03 },
      { "hour": 6, "price": 122.18 },
      { "hour": 7, "price": 148.44 },
      { "hour": 8, "price": 170.18 },
      { "hour": 9, "price": 132.58 },
      { "hour": 10, "price": 96.54 },
      { "hour": 11, "price": 68.24 },
      { "hour": 12, "price": 59.02 },
      { "hour": 13, "price": 57.9 },
      { "hour": 14, "price": 58.21 },
      { "hour": 15, "price": 61.25 },
      { "hour": 16, "price": 88.27 },
      { "hour": 17, "price": 124.57 },
      { "hour": 18, "price": 175.44 },
      { "hour": 19, "price": 189.94 },
      { "hour": 20, "price": 153.86 },
      { "hour": 21, "price": 147.88 },
      { "hour": 22, "price": 131.82 },
      { "hour": 23, "price": 132 }
    ]
  }
}
