{
  "date": "2026-02-03",
  "unit": "EUR/MWh",
  "zones": {
    "LV": [
      { "hour": 0, "price": 180.59 },
      { "hour": 1, "price": 143.85 },
      { "hour": 2, "price": 150.06 },
      { "hour": 3, "price": 150.06 },
      { "hour": 4, "price": 150.06 },
      { "hour": 5, "price": 210.23 },
      { "hour": 6, "price": 328.45 },
      { "hour": 7, "price": 480.79 },
      { "hour": 8, "price": 479.76 },
      { "hour": 9, "price": 478.88 },
      { "hour": 10, "price": 458.89 },
      { "hour": 11, "price": 478.48 },
      { "hour": 12, "price": 442.59 },
      { "hour": 13, "price": 489.99 },
      { "hour": 14, "price": 447.52 },
      { "hour": 15, "price": 484.48 },
      { "hour": 16, "price": 496.98 },
      { "hour": 17, "price": 614.46 },
      { "hour": 18, "price": 492.39 },
      { "hour": 19, "price": 494.15 },
      { "hour": 20, "price": 489.72 },
      { "hour": 21, "price": 401.79 },
      { "hour": 22, "price": 327.36 },
      { "hour": 23, "price": 377.01 }
    ],
    "EE": [
      { "hour": 0, "price": 180.59 },
      { "hour": 1, "price": 143.85 },
      { "hour": 2, "price": 150.06 },
      { "hour": 3, "price": 150.06 },
      { "hour": 4, "price": 150.06 },
      { "hour": 5, "price": 210.23 },
      { "hour": 6, "price": 328.45 },
      { "hour": 7, "price": 480.79 },
      { "hour": 8, "price": 479.76 },
      { "hour": 9, "price": 478.88 },
      { "hour": 10, "price": 458.89 },
      { "hour": 11, "price": 478.48 },
      { "hour": 12, "price": 442.59 },
      { "hour": 13, "price": 489.99 },
      { "hour": 14, "price": 447.52 },
      { "hour": 15, "price": 484.48 },
      { "hour": 16, "price": 496.98 },
      { "hour": 17, "price": 614.46 },
      { "hour": 18, "price": 492.39 },
      { "hour": 19, "price": 494.15 },
      { "hour": 20, "price": 489.72 },
      { "hour": 21, "price": 401.79 },
      { "hour": 22, "price": 327.36 },
      { "hour": 23, "price": 377.01 }
    ],
    "LT": [
      { "hour": 0, "price": 180.59 },
      { "hour": 1, "price": 143.85 },
      { "hour": 2, "price": 150.06 },
      { "hour": 3, "price": 150.06 },
      { "hour": 4, "price": 150.06 },
      { "hour": 5, "price": 210.23 },
      { "hour": 6, "price": 328.45 },
      { "hour": 7, "price": 480.79 },
      { "hour": 8, "price": 479.76 },
      { "hour": 9, "price": 478.88 },
      { "hour": 10, "price": 458.89 },
      { "hour": 11, "price": 478.48 },
      { "hour": 12, "price": 442.59 },
      { "hour": 13, "price": 489.99 },
      { "hour": 14, "price": 447.52 },
      { "hour": 15, "price": 484.48 },
      { "hour": 16, "price": 496.98 },
      { "hour": 17, "price": 614.46 },
      { "hour": 18, "price": 492.39 },
      { "hour": 19, "price": 494.15 },
      { "hour": 20, "price": 489.72 },
      { "hour": 21, "price": 401.79 },
      { "hour": 22, "price": 327.36 },
      { "hour": 23, "price": 377.01 }
    ]
  }
}
