{
  "date": "2026-04-28",
  "unit": "EUR/MWh",
  "zones": {
    "LV": [
      { "hour": 0, "price": 80.38 },
      { "hour": 1, "price": 81.82 },
      { "hour": 2, "price": 65.5 },
      { "hour": 3, "price": 50 },
      { "hour": 4, "price": 50.99 },
      { "hour": 5, "price": 56.31 },
      { "hour": 6, "price": 60.96 },
      { "hour": 7, "price": 97.97 },
      { "hour": 8, "price": 57.75 },
      { "hour": 9, "price": 17.54 },
      { "hour": 10, "price": 9.26 },
      { "hour": 11, "price": 5.84 },
      { "hour": 12, "price": 5.42 },
      { "hour": 13, "price": 5.15 },
      { "hour": 14, "price": 4.99 },
      { "hour": 15, "price": 5.03 },
      { "hour": 16, "price": 5.14 },
      { "hour": 17, "price": 6.53 },
      { "hour": 18, "price": 33.66 },
      { "hour": 19, "price": 93.75 },
      { "hour": 20, "price": 123.12 },
      { "hour": 21, "price": 124.31 },
      { "hour": 22, "price": 119.78 },
      { "hour": 23, "price": 112.48 }
    ],
    "EE": [
      { "hour": 0, "price": 6.74 },
      { "hour": 1, "price": 7.39 },
      { "hour": 2, "price": 7.22 },
      { "hour": 3, "price": 7.22 },
      { "hour": 4, "price": 7.26 },
      { "hour": 5, "price": 8.13 },
      { "hour": 6, "price": 13.79 },
      { "hour": 7, "price": 18.78 },
      { "hour": 8, "price": 18.22 },
      { "hour": 9, "price": 17.54 },
      { "hour": 10, "price": 9.26 },
      { "hour": 11, "price": 6.02 },
      { "hour": 12, "price": 5.42 },
      { "hour": 13, "price": 5.15 },
      { "hour": 14, "price": 4.99 },
      { "hour": 15, "price": 5.03 },
      { "hour": 16, "price": 5.14 },
      { "hour": 17, "price": 6.53 },
      { "hour": 18, "price": 16.32 },
      { "hour": 19, "price": 46.17 },
      { "hour": 20, "price": 120.94 },
      { "hour": 21, "price": 99.73 },
      { "hour": 22, "price": 108.67 },
      { "hour": 23, "price": 112.48 }
    ],
    "LT": [
      { "hour": 0, "price": 80.38 },
      { "hour": 1, "price": 81.82 },
      { "hour": 2, "price": 65.5 },
      { "hour": 3, "price": 50 },
      { "hour": 4, "price": 50.99 },
      { "hour": 5, "price": 56.31 },
      { "hour": 6, "price": 60.96 },
      { "hour": 7, "price": 97.97 },
      { "hour": 8, "price": 57.75 },
      { "hour": 9, "price": 17.54 },
      { "hour": 10, "price": 9.26 },
      { "hour": 11, "price": 5.84 },
      { "hour": 12, "price": 5.42 },
      { "hour": 13, "price": 5.15 },
      { "hour": 14, "price": 4.99 },
      { "hour": 15, "price": 5.03 },
      { "hour": 16, "price": 5.14 },
      { "hour": 17, "price": 6.53 },
      { "hour": 18, "price": 33.66 },
      { "hour": 19, "price": 93.75 },
      { "hour": 20, "price": 123.12 },
      { "hour": 21, "price": 124.31 },
      { "hour": 22, "price": 119.78 },
      { "hour": 23, "price": 112.48 }
    ]
  }
}
